commerce/__init__.py
commerce/admin.py
commerce/apps.py
commerce/tests.py
commerce/urls.py
commerce/models/__init__.py
commerce/models/category.py
commerce/models/core.py
commerce/models/order.py
commerce/models/product.py
commerce/serializers/category_serializer.py
commerce/serializers/order_serializer.py
commerce/serializers/product_serializer.py
commerce/utils/enum.py
commerce/utils/filter.py
commerce/utils/permissions.py
commerce/utils/response.py
commerce/views/category_view.py
commerce/views/order_view.py
commerce/views/product_view.py
dj_rest_commerce-1.0.dist-info/LICENSE
dj_rest_commerce-1.0.dist-info/METADATA
dj_rest_commerce-1.0.dist-info/WHEEL
dj_rest_commerce-1.0.dist-info/top_level.txt
dj_rest_commerce-1.0.dist-info/RECORD
